{"_id":{"$oid":"6182ce8097bd93a43975b1cd"},"id":"s1","email":"s1@gmail.com","Name":"s1","Mobile":{"$numberInt":"1234"},"batch_id":"B1","mentor_id":{"$numberInt":"1"}}
{"_id":{"$oid":"6182ce8097bd93a43975b1ce"},"id":"s10","email":"s10@gmail.com","Name":"s10","Mobile":{"$numberInt":"1238"},"batch_id":"B3","mentor_id":{"$numberInt":"3"}}
{"_id":{"$oid":"6182ce8097bd93a43975b1cf"},"id":"s2","email":"s2@gmail.com","Name":"s2","Mobile":{"$numberInt":"1235"},"batch_id":"B1","mentor_id":{"$numberInt":"1"}}
{"_id":{"$oid":"6182ce8097bd93a43975b1d0"},"id":"s3","email":"s3@gmail.com","Name":"s3","Mobile":{"$numberInt":"1236"},"batch_id":"B1","mentor_id":{"$numberInt":"1"}}
{"_id":{"$oid":"6182ce8097bd93a43975b1d1"},"id":"s4","email":"s4@gmail.com","Name":"s4","Mobile":{"$numberInt":"1237"},"batch_id":"B1","mentor_id":{"$numberInt":"1"}}
{"_id":{"$oid":"6182ce8097bd93a43975b1d2"},"id":"s5","email":"s5@gmail.com","Name":"s5","Mobile":{"$numberInt":"1238"},"batch_id":"B1","mentor_id":{"$numberInt":"1"}}
{"_id":{"$oid":"6182ce8097bd93a43975b1d3"},"id":"s6","email":"s6@gmail.com","Name":"s6","Mobile":{"$numberInt":"1234"},"batch_id":"B2","mentor_id":{"$numberInt":"2"}}
{"_id":{"$oid":"6182ce8097bd93a43975b1d4"},"id":"s7","email":"s7@gmail.com","Name":"s7","Mobile":{"$numberInt":"1235"},"batch_id":"B2","mentor_id":{"$numberInt":"2"}}
{"_id":{"$oid":"6182ce8097bd93a43975b1d5"},"id":"s8","email":"s8@gmail.com","Name":"s8","Mobile":{"$numberInt":"1236"},"batch_id":"B2","mentor_id":{"$numberInt":"2"}}
{"_id":{"$oid":"6182ce8097bd93a43975b1d6"},"id":"s9","email":"s9@gmail.com","Name":"s9","Mobile":{"$numberInt":"1237"},"batch_id":"B3","mentor_id":{"$numberInt":"3"}}
